pyperclip_cli/__init__.py
pyperclip_cli/cli.py
pyperclip_cli-0.1.2.dist-info/entry_points.txt
pyperclip_cli-0.1.2.dist-info/WHEEL
pyperclip_cli-0.1.2.dist-info/METADATA
pyperclip_cli-0.1.2.dist-info/RECORD
