Metadata-Version: 2.1
Name: pyperclip-cli
Version: 0.1.2
Summary: Pyperclip CLI - cross-platform clipboard utility
Home-page: https://github.com/tddschn/pyperclip-cli
License: MIT
Keywords: clipboard,clipboard-cli,cli,pyperclip
Author: Xinyuan Chen
Author-email: 45612704+tddschn@users.noreply.github.com
Requires-Python: >=3.10,<4.0
Classifier: License :: OSI Approved :: MIT License
Classifier: Programming Language :: Python :: 3
Classifier: Programming Language :: Python :: 3.10
Classifier: Topic :: Utilities
Requires-Dist: pyperclip (>=1.8.2,<2.0.0)
Project-URL: Bug Tracker, https://github.com/tddschn/pyperclip-cli/issues
Project-URL: Repository, https://github.com/tddschn/pyperclip-cli
